{
  "project_info": {
    "project_number": "546004591088",
    "firebase_url": "https://typemate-95306.firebaseio.com",
    "project_id": "typemate-95306",
    "storage_bucket": "typemate-95306.appspot.com"
  },
  "client": [
    {
      "client_info": {
        "mobilesdk_app_id": "1:546004591088:android:d0e4d9dbd94da1ee56bd35",
        "android_client_info": {
          "package_name": "com.mbti.typemate"
        }
      },
      "oauth_client": [
        {
          "client_id": "546004591088-hlfcivd9kai3hbnknsneld81d999sogb.apps.googleusercontent.com",
          "client_type": 1,
          "android_info": {
            "package_name": "com.mbti.typemate",
            "certificate_hash": "c1dd575396dd57f5f655cde7109d103030ba1ac4"
          }
        },
        {
          "client_id": "546004591088-emjs603tbrp0aolipec6nti4c5b1cnkk.apps.googleusercontent.com",
          "client_type": 1,
          "android_info": {
            "package_name": "com.mbti.typemate",
            "certificate_hash": "0adca3a1e4de4f4c26f9783e1f0b91bbea95ba70"
          }
        },
        {
          "client_id": "546004591088-82j1dshe84ua4sq59t66c93q4ntqb1vj.apps.googleusercontent.com",
          "client_type": 3
        }
      ],
      "api_key": [
        {
          "current_key": "AIzaSyA8gNP6N41zWWH4OAefox-RnhscdnApmsE"
        }
      ],
      "services": {
        "appinvite_service": {
          "other_platform_oauth_client": [
            {
              "client_id": "546004591088-82j1dshe84ua4sq59t66c93q4ntqb1vj.apps.googleusercontent.com",
              "client_type": 3
            }
          ]
        }
      }
    }
  ],
  "configuration_version": "1"
}